babappaomega/__init__.py
babappaomega/cli.py
babappaomega/encoding.py
babappaomega/inference.py
babappaomega/interpret.py
babappaomega/models.py
babappaomega/tree.py
babappaomega/utils.py
babappaomega-1.2.1.dist-info/licenses/LICENSE
babappaomega-1.2.1.dist-info/METADATA
babappaomega-1.2.1.dist-info/WHEEL
babappaomega-1.2.1.dist-info/entry_points.txt
babappaomega-1.2.1.dist-info/top_level.txt
babappaomega-1.2.1.dist-info/RECORD
