Metadata-Version: 2.4
Name: babappaomega
Version: 1.2.1
Summary: BABAPPAΩ: Likelihood-free branch-aware episodic selection burden inference
Author: Krishnendu Sinha
License: MIT
Project-URL: Homepage, https://github.com/krishnendusinha/babappaomega
Project-URL: Documentation, https://github.com/krishnendusinha/babappaomega
Project-URL: Source, https://github.com/krishnendusinha/babappaomega
Project-URL: Zenodo, https://doi.org/10.5281/zenodo.18195869
Keywords: positive selection,branch-site model,evolutionary genomics,likelihood-free inference,deep learning,phylogenetics
Classifier: Development Status :: 5 - Production/Stable
Classifier: Intended Audience :: Science/Research
Classifier: Topic :: Scientific/Engineering :: Bio-Informatics
Classifier: License :: OSI Approved :: MIT License
Classifier: Programming Language :: Python :: 3
Classifier: Programming Language :: Python :: 3.9
Classifier: Programming Language :: Python :: 3.10
Classifier: Programming Language :: Python :: 3.11
Classifier: Operating System :: OS Independent
Requires-Python: >=3.9
License-File: LICENSE
Requires-Dist: torch>=2.0
Requires-Dist: numpy
Requires-Dist: biopython
Requires-Dist: ete3
Requires-Dist: six
Requires-Dist: platformdirs
Dynamic: license-file
